Workbook

Sheet Backlog
A1: № задачи | B1: Фаза | C1: Модуль | D1: Название задачи | E1: Приоритет | F1: Зависимости | G1: Результат (deliverable) | H1: Критерии готовности (DoD) | I1: Оценка, ч
A2: F001 | B2: 0. Foundation | C2: Foundation | D2: Инициализировать монорепозиторий (backend/, frontend/, pyproject.toml, package.json) | E2: P0 | F2: — | G2: Скелет репозитория с двумя корневыми папками | H2: Репозиторий клонируется, обе папки существуют, README с описанием структуры | I2: 1
A3: F002 | B3: 0. Foundation | C3: Foundation | D3: Настроить ruff/black/mypy для backend | E3: P0 | F3: F001 | G3: Конфиги ruff.toml/mypy.ini + Makefile-таргет lint | H3: make lint проходит на пустом проекте без ошибок | I3: 1
A4: F003 | B4: 0. Foundation | C4: Foundation | D4: Настроить ESLint/Prettier для frontend | E4: P0 | F4: F001 | G4: eslint.config.js + prettier config | H4: npm run lint проходит на пустом Next.js проекте | I4: 1
A5: F004 | B5: 0. Foundation | C5: Foundation | D5: Docker-compose для локальной разработки (Postgres 16, Redis 7) | E5: P0 | F5: F001 | G5: docker-compose.yml | H5: docker compose up поднимает Postgres и Redis, health-check зелёный | I5: 2
A6: F005 | B6: 0. Foundation | C6: Foundation | D6: Настроить pre-commit hooks (lint+format при коммите) | E6: P1 | F6: F002,F003 | G6: .pre-commit-config.yaml | H6: Коммит с ошибкой линта блокируется локально | I6: 1
A7: F006 | B7: 0. Foundation | C7: Foundation | D7: CI-скелет: GitHub Actions, job lint+test на PR | E7: P0 | F7: F002,F003 | G7: .github/workflows/ci.yml | H7: PR с намеренной ошибкой линта получает красный статус | I7: 2
A8: F007 | B8: 0. Foundation | C8: Foundation | D8: pydantic-settings BaseSettings (DSN БД, Redis URL, JWT-ключ) | E8: P0 | F8: F001 | G8: composition/settings.py | H8: Приложение падает с понятной ошибкой при отсутствии обязательной переменной окружения | I8: 1
A9: F008 | B9: 0. Foundation | C9: Foundation | D9: building_blocks/domain: базовые Entity, AggregateRoot, ValueObject, DomainEvent | E9: P0 | F9: F001 | G9: Пакет building_blocks/domain | H9: Модульный тест создаёт наследника AggregateRoot и проверяет накопление доменных событий | I9: 2
A10: F009 | B10: 0. Foundation | C10: Foundation | D10: building_blocks/application: Protocol Command/Query/Handler | E10: P0 | F10: F008 | G10: Пакет building_blocks/application | H10: mypy проходит на примере фиктивного Command+Handler | I10: 1
A11: F010 | B11: 0. Foundation | C11: Foundation | D11: building_blocks/infrastructure: Protocol UnitOfWork/EventBus/Clock | E11: P0 | F11: F008 | G11: Пакет building_blocks/infrastructure | H11: Фиктивная in-memory реализация каждого Protocol проходит тест на соответствие интерфейсу | I11: 2
A12: F011 | B12: 0. Foundation | C12: Foundation | D12: composition/settings.py подключён к остальным пакетам | E12: P0 | F12: F007 | G12: Settings импортируется без циклических зависимостей | H12: import-граф не содержит циклов (проверка вручную/скриптом) | I12: 1
A13: F012 | B13: 0. Foundation | C13: Foundation | D13: composition/api_app.py — пустой FastAPI() с health-check | E13: P0 | F13: F011 | G13: GET /health возвращает 200 | H13: uvicorn composition.api_app:app стартует, /health отвечает status ok | I13: 1
... A251: OPS020 | B251: 12. Ops/QA | C251: Ops | D251: Итоговый README, связывающий все документы проекта | E251: P3 | F251: OPS019 | G251: README.md | H251: Документ содержит ссылки на все предыдущие артефакты проекта | I251: 1

Sheet Summary
A1: Сводка бэклога реализации
A3: Всего задач: | B3: =COUNTA(Backlog!A2:A251) -> 250
A4: Суммарная оценка, часов: | B4: =SUM(Backlog!I2:I251) -> 396
A5: Суммарная оценка, человеко-недель (40ч/нед): | B5: =B4/40 -> 9.9
A7: По приоритету
A8: Приоритет | B8: Кол-во задач | C8: Часов
A9: P0 | B9: =COUNTIF(Backlog!E2:E251,A9) -> 144 | C9: =SUMIF(Backlog!E2:E251,A9,Backlog!I2:I251) -> 231
A10: P1 | B10: =COUNTIF(Backlog!E2:E251,A10) -> 72 | C10: =SUMIF(Backlog!E2:E251,A10,Backlog!I2:I251) -> 115
A11: P2 | B11: =COUNTIF(Backlog!E2:E251,A11) -> 33 | C11: =SUMIF(Backlog!E2:E251,A11,Backlog!I2:I251) -> 49
A12: P3 | B12: =COUNTIF(Backlog!E2:E251,A12) -> 1 | C12: =SUMIF(Backlog!E2:E251,A12,Backlog!I2:I251) -> 1
A14: По модулю
A15: Модуль | B15: Кол-во задач | C15: Часов
A16: Foundation | B16: =COUNTIF(Backlog!C2:C251,A16) -> 15 | C16: =SUMIF(Backlog!C2:C251,A16,Backlog!I2:I251) -> 21
A17: DB | B17: =COUNTIF(Backlog!C2:C251,A17) -> 20 | C17: =SUMIF(Backlog!C2:C251,A17,Backlog!I2:I251) -> 32
A18: RuleEngine | B18: =COUNTIF(Backlog!C2:C251,A18) -> 15 | C18: =SUMIF(Backlog!C2:C251,A18,Backlog!I2:I251) -> 25
A19: LegalRules | B19: =COUNTIF(Backlog!C2:C251,A19) -> 15 | C19: =SUMIF(Backlog!C2:C251,A19,Backlog!I2:I251) -> 24
A20: Personnel | B20: =COUNTIF(Backlog!C2:C251,A20) -> 15 | C20: =SUMIF(Backlog!C2:C251,A20,Backlog!I2:I251) -> 23
A21: ServiceCalendar | B21: =COUNTIF(Backlog!C2:C251,A21) -> 8 | C21: =SUMIF(Backlog!C2:C251,A21,Backlog!I2:I251) -> 11
A22: Scheduling | B22: =COUNTIF(Backlog!C2:C251,A22) -> 15 | C22: =SUMIF(Backlog!C2:C251,A22,Backlog!I2:I251) -> 23
A23: TimeAccounting | B23: =COUNTIF(Backlog!C2:C251,A23) -> 35 | C23: =SUMIF(Backlog!C2:C251,A23,Backlog!I2:I251) -> 57
A24: Compensation | B24: =COUNTIF(Backlog!C2:C251,A24) -> 20 | C24: =SUMIF(Backlog!C2:C251,A24,Backlog!I2:I251) -> 32
A25: RestBalance | B25: =COUNTIF(Backlog!C2:C251,A25) -> 12 | C25: =SUMIF(Backlog!C2:C251,A25,Backlog!I2:I251) -> 17
A26: LeaveManagement | B26: =COUNTIF(Backlog!C2:C251,A26) -> 15 | C26: =SUMIF(Backlog!C2:C251,A26,Backlog!I2:I251) -> 24
A27: Frontend | B27: =COUNTIF(Backlog!C2:C251,A27) -> 45 | C27: =SUMIF(Backlog!C2:C251,A27,Backlog!I2:I251) -> 76
A28: Ops | B28: =COUNTIF(Backlog!C2:C251,A28) -> 20 | C28: =SUMIF(Backlog!C2:C251,A28,Backlog!I2:I251) -> 31
